ucs/__init__.py
ucs/constants.py
ucs/functions.py
ucs/symbolic.py
ucs-0.3.dist-info/DESCRIPTION.rst
ucs-0.3.dist-info/METADATA
ucs-0.3.dist-info/RECORD
ucs-0.3.dist-info/WHEEL
ucs-0.3.dist-info/metadata.json
ucs-0.3.dist-info/top_level.txt
