Metadata-Version: 2.0
Name: ucs
Version: 0.3
Summary: Implements the CAM02-UCS forward transform symbolically, using Theano.
Home-page: https://github.com/crowsonkb/ucs
Author: Katherine Crowson
Author-email: crowsonkb@gmail.com
License: MIT
Download-URL: https://github.com/crowsonkb/ucs/archive/0.3.zip
Keywords: ciecam02 cam02 cam02-ucs color science
Platform: UNKNOWN
Classifier: Development Status :: 3 - Alpha
Classifier: Intended Audience :: Science/Research
Classifier: License :: OSI Approved :: MIT License
Classifier: Programming Language :: Python :: 3
Classifier: Programming Language :: Python :: 3.5
Classifier: Programming Language :: Python :: 3.6
Classifier: Topic :: Multimedia :: Graphics
Classifier: Topic :: Scientific/Engineering
Requires-Dist: Theano (>=0.9.0)
Requires-Dist: numpy (>=1.12.1)
Requires-Dist: scipy (>=0.19.0)
